image_sky/__init__.py
image_sky/default_config.yaml
image_sky/ec2standalone.py
image_sky/executor.py
image_sky/fun_client.py
image_sky/future.py
image_sky/invokers.py
image_sky/local.py
image_sky/queues.py
image_sky/runtime.py
image_sky/version.py
image_sky/wait.py
image_sky/wren.py
image_sky/wrenconfig.py
image_sky/wrenhandler.py
image_sky/wrenlogging.py
image_sky/wrenutil.py
image_sky/ec2_standalone_files/cloudwatch-agent.config
image_sky/ec2_standalone_files/ec2standalone.cloudinit.template
image_sky/ec2_standalone_files/supervisord.conf
image_sky/ec2_standalone_files/supervisord.init
image_sky/jobrunner/__init__.py
image_sky/jobrunner/jobrunner.py
image_sky/scripts/__init__.py
image_sky/scripts/pywrencli.py
image_sky/scripts/setupscript.py
image_sky/scripts/standalone.py
image_sky/serialize/__init__.py
image_sky/serialize/default_preinstalls.py
image_sky/serialize/module_dependency.py
image_sky/serialize/serialize.py
image_sky/serialize/util.py
image_sky/serialize/cloudpickle/__init__.py
image_sky/serialize/cloudpickle/cloudpickle.py
image_sky/storage/OssBackend.py
image_sky/storage/__init__.py
image_sky/storage/exceptions.py
image_sky/storage/s3_backend.py
image_sky/storage/storage.py
image_sky/storage/storage_utils.py
image_sky-0.6.0.dist-info/LICENSE
image_sky-0.6.0.dist-info/METADATA
image_sky-0.6.0.dist-info/WHEEL
image_sky-0.6.0.dist-info/dependency_links.txt
image_sky-0.6.0.dist-info/entry_points.txt
image_sky-0.6.0.dist-info/top_level.txt
image_sky-0.6.0.dist-info/RECORD
